tetras_toolbox/__init__.py
tetras_toolbox/_type_t.py
tetras_toolbox/fixed_point.py
tetras_toolbox/interact.py
tetras_toolbox-0.1.1.dist-info/LICENSE
tetras_toolbox-0.1.1.dist-info/METADATA
tetras_toolbox-0.1.1.dist-info/WHEEL
tetras_toolbox-0.1.1.dist-info/top_level.txt
tetras_toolbox-0.1.1.dist-info/RECORD
