Metadata-Version: 2.1
Name: tetras-toolbox
Version: 0.1.1
Summary: My personal collection of itertools-based "convenience" functions. 
Author-email: TetraKetra <tetra.silv@gmail.com>
Project-URL: Homepage, https://github.com/tetraketra/tetras-toolbox
Project-URL: Bug Tracker, https://github.com/tetraketra/tetras-toolbox
Classifier: Programming Language :: Python :: 3
Classifier: License :: OSI Approved :: GNU General Public License v3 or later (GPLv3+)
Classifier: Operating System :: OS Independent
Classifier: Intended Audience :: Developers
Requires-Python: >=3.10
License-File: LICENSE
Requires-Dist: more-itertools >=8.10.0
